fuid.py
fuid-0.8.dist-info/METADATA
fuid-0.8.dist-info/WHEEL
fuid-0.8.dist-info/top_level.txt
fuid-0.8.dist-info/RECORD
