Metadata-Version: 2.1
Name: fuid
Version: 0.8
Summary: Fast, scalable unique ID generation
Home-page: http://github.com/husseinraed/fuid.py
Author: Hussein Raed
Author-email: me@husseinraed.cf
License: UNKNOWN
Platform: UNKNOWN
Classifier: Development Status :: 4 - Beta
Classifier: Intended Audience :: Developers
Classifier: License :: OSI Approved :: Apache Software License
Classifier: Operating System :: POSIX
Classifier: Programming Language :: Python
Classifier: Programming Language :: Python :: 3
Classifier: Topic :: Internet :: WWW/HTTP
Classifier: Topic :: Software Development :: Libraries :: Python Modules
